HISTORY.rst
LICENSE
MANIFEST.in
README.md
setup.cfg
setup.py
flask_nameko/__init__.py
flask_nameko/connection_pool.py
flask_nameko/errors.py
flask_nameko/proxies.py
flask_nameko.egg-info/PKG-INFO
flask_nameko.egg-info/SOURCES.txt
flask_nameko.egg-info/dependency_links.txt
flask_nameko.egg-info/not-zip-safe
flask_nameko.egg-info/requires.txt
flask_nameko.egg-info/top_level.txt
tests/test_connection_pool.py
tests/test_flask_pooled_cluster_rpc_proxy.py