Metadata-Version: 1.0
Name: flask-nameko
Version: 1.4.0
Summary: A wrapper for using nameko services with Flask
Home-page: https://github.com/clef/flask_nameko
Author: Jesse Pollak
Author-email: jesse@getclef.com
License: ISCL
Keywords: flask_nameko
Platform: UNKNOWN
